{"status":"OK","message":"Request Processed Successfully","timeRanges":[{"periodFrom":"11-09-2014","periodTo":"11-15-2014","periodName":"weekly","reportingInterval":"daily","groupDetail":[{"groupBy":"usrGrp1","groupName":"Musicians","data":[{"date":"10-26-2014","noOfUsers":"698"},{"date":"11-02-2014","noOfUsers":"681"},{"date":"11-09-2014","noOfUsers":"674"},{"date":"11-16-2014","noOfUsers":"701"},{"date":"11-23-2014","noOfUsers":"679"}]},{"groupBy":"usrGrp2","groupName":"Professional","data":[{"date":"10-26-2014","noOfUsers":"420"},{"date":"11-02-2014","noOfUsers":"443"},{"date":"11-09-2014","noOfUsers":"437"},{"date":"11-16-2014","noOfUsers":"448"},{"date":"11-23-2014","noOfUsers":"426"}]},{"groupBy":"usrGrp3","groupName":"Finance Executives","data":[{"date":"10-26-2014","noOfUsers":"480"},{"date":"11-02-2014","noOfUsers":"508"},{"date":"11-09-2014","noOfUsers":"532"},{"date":"11-16-2014","noOfUsers":"558"},{"date":"11-23-2014","noOfUsers":"570"}]},{"groupBy":"usrGrp4","groupName":"Project Managers","data":[{"date":"10-26-2014","noOfUsers":"856"},{"date":"11-02-2014","noOfUsers":"880"},{"date":"11-09-2014","noOfUsers":"908"},{"date":"11-16-2014","noOfUsers":"922"},{"date":"11-23-2014","noOfUsers":"892"}]},{"groupBy":"usrGrp5","groupName":"Photographers","data":[{"date":"10-26-2014","noOfUsers":"655"},{"date":"11-02-2014","noOfUsers":"675"},{"date":"11-09-2014","noOfUsers":"665"},{"date":"11-16-2014","noOfUsers":"695"},{"date":"11-23-2014","noOfUsers":"673"}]}]},{"periodFrom":"11-09-2014","periodTo":"11-15-2014","periodName":"monthly","reportingInterval":"daily","groupDetail":[{"groupBy":"usrGrp1","groupName":"Musicians","data":[{"date":"9-1-2014","noOfUsers":"2790"},{"date":"10-1-2014","noOfUsers":"2724"},{"date":"11-1-2014","noOfUsers":"2696"},{"date":"12-1-2014","noOfUsers":"2804"},{"date":"1-1-2015","noOfUsers":"2716"}]},{"groupBy":"usrGrp2","groupName":"Professional","data":[{"date":"9-1-2014","noOfUsers":"1678"},{"date":"10-1-2014","noOfUsers":"1772"},{"date":"11-1-2014","noOfUsers":"1748"},{"date":"12-1-2014","noOfUsers":"1792"},{"date":"1-1-2015","noOfUsers":"1704"}]},{"groupBy":"usrGrp3","groupName":"Finance Executives","data":[{"date":"9-1-2014","noOfUsers":"1921"},{"date":"10-1-2014","noOfUsers":"2032"},{"date":"11-1-2014","noOfUsers":"2128"},{"date":"12-1-2014","noOfUsers":"2232"},{"date":"1-1-2015","noOfUsers":"2280"}]},{"groupBy":"usrGrp4","groupName":"Project Managers","data":[{"date":"9-1-2014","noOfUsers":"3426"},{"date":"10-1-2014","noOfUsers":"3520"},{"date":"11-1-2014","noOfUsers":"3632"},{"date":"12-1-2014","noOfUsers":"3688"},{"date":"1-1-2015","noOfUsers":"3568"}]},{"groupBy":"usrGrp5","groupName":"Photographers","data":[{"date":"9-1-2014","noOfUsers":"2618"},{"date":"10-1-2014","noOfUsers":"2700"},{"date":"11-1-2014","noOfUsers":"2660"},{"date":"12-1-2014","noOfUsers":"2780"},{"date":"1-1-2015","noOfUsers":"2692"}]}]},{"periodFrom":"11-09-2014","periodTo":"11-15-2014","periodName":"quarterly","reportingInterval":"daily","groupDetail":[{"groupBy":"usrGrp1","groupName":"Musicians","data":[{"date":"4-1-2014","noOfUsers":"8370"},{"date":"7-1-2014","noOfUsers":"8172"},{"date":"10-1-2014","noOfUsers":"8088"},{"date":"1-1-2015","noOfUsers":"8412"},{"date":"4-1-2015","noOfUsers":"8148"}]},{"groupBy":"usrGrp2","groupName":"Professional","data":[{"date":"4-1-2014","noOfUsers":"5035"},{"date":"7-1-2014","noOfUsers":"5316"},{"date":"10-1-2014","noOfUsers":"5244"},{"date":"1-1-2015","noOfUsers":"5376"},{"date":"4-1-2015","noOfUsers":"5112"}]},{"groupBy":"usrGrp3","groupName":"Finance Executives","data":[{"date":"4-1-2014","noOfUsers":"5763"},{"date":"7-1-2014","noOfUsers":"6096"},{"date":"10-1-2014","noOfUsers":"6384"},{"date":"1-1-2015","noOfUsers":"6696"},{"date":"4-1-2015","noOfUsers":"6840"}]},{"groupBy":"usrGrp4","groupName":"Project Managers","data":[{"date":"4-1-2014","noOfUsers":"10277"},{"date":"7-1-2014","noOfUsers":"10560"},{"date":"10-1-2014","noOfUsers":"10896"},{"date":"1-1-2015","noOfUsers":"11064"},{"date":"4-1-2015","noOfUsers":"10704"}]},{"groupBy":"usrGrp5","groupName":"Photographers","data":[{"date":"4-1-2014","noOfUsers":"7854"},{"date":"7-1-2014","noOfUsers":"8100"},{"date":"10-1-2014","noOfUsers":"7980"},{"date":"1-1-2015","noOfUsers":"8340"},{"date":"4-1-2015","noOfUsers":"8076"}]}]},{"periodFrom":"11-09-2014","periodTo":"11-15-2014","periodName":"yearly","reportingInterval":"daily","groupDetail":[{"groupBy":"usrGrp1","groupName":"Musicians","data":[{"date":"1-1-2012","noOfUsers":"33482"},{"date":"1-1-2013","noOfUsers":"32688"},{"date":"1-1-2014","noOfUsers":"32352"},{"date":"1-1-2015","noOfUsers":"33648"}]},{"groupBy":"usrGrp2","groupName":"Professional","data":[{"date":"1-1-2012","noOfUsers":"20142"},{"date":"1-1-2013","noOfUsers":"21264"},{"date":"1-1-2014","noOfUsers":"20976"},{"date":"1-1-2015","noOfUsers":"21504"}]},{"groupBy":"usrGrp3","groupName":"Finance Executives","data":[{"date":"1-1-2012","noOfUsers":"23051"},{"date":"1-1-2013","noOfUsers":"24384"},{"date":"1-1-2014","noOfUsers":"25536"},{"date":"1-1-2015","noOfUsers":"26784"}]},{"groupBy":"usrGrp4","groupName":"Project Managers","data":[{"date":"1-1-2012","noOfUsers":"41106"},{"date":"1-1-2013","noOfUsers":"42240"},{"date":"1-1-2014","noOfUsers":"43584"},{"date":"1-1-2015","noOfUsers":"44256"}]},{"groupBy":"usrGrp5","groupName":"Photographers","data":[{"date":"1-1-2012","noOfUsers":"31417"},{"date":"1-1-2013","noOfUsers":"32400"},{"date":"1-1-2014","noOfUsers":"31920"},{"date":"1-1-2015","noOfUsers":"33360"}]}]}]}